Workbook

Sheet Project Plan
A1: SEJEL Restaurant — Point of Sale
A2: Project plan · delivered scope and remaining scope
A3: Branch: Olaya · Prepared 12 Aug 2026 · Dates for delivered work are the actual commit dates. Dates for remaining work are ESTIMATES (blue), on a Sunday–Thursday working week.
A5: ID | B5: Phase | C5: Workstream | D5: Scope / deliverable | E5: Status | F5: Owner | G5: Effort (working days) | H5: Start | I5: Finish | J5: Calendar days | K5: % complete | L5: Evidence / notes
A6: 1 | B6: Foundations | C6: Architecture & repository | D6: Flutter till, FastAPI backend, ZATCA library, PixelPoint migration — one repo, four parts | E6: Done | F6: Development | G6: 1 | H6: 46238 | I6: 46238 | J6: =I6-H6+1 -> 1 | K6: 1 | L6: commit 6cdfe13
A7: 2 | B7: Foundations | C7: ZATCA signing on the device | D7: Dart signer pinned byte-for-byte to the Python reference via golden vectors | E7: Done | F7: Development | G7: 0.16 | H7: 46239 | I7: 46239 | J7: =I7-H7+1 -> 1 | K7: 1 | L7: commit 86c4bc1
A8: 3 | B8: Foundations | C8: Printer Setup | D8: Device setup screen: printer address, port, test slip through the real ESC/POS builder | E8: Done | F8: Development | G8: 0.16 | H8: 46239 | I8: 46239 | J8: =I8-H8+1 -> 1 | K8: 1 | L8: commits b2c8370, 69c4df3
A9: 4 | B9: Foundations | C9: Windows desktop target | D9: The till runs as a Windows application | E9: Done | F9: Development | G9: 0.16 | H9: 46239 | I9: 46239 | J9: =I9-H9+1 -> 1 | K9: 1 | L9: commit eb84074
A10: 5 | B10: Foundations | C10: Till Setup / device enrolment | D10: Enrolment codes, device identity, roles (till / KDS / CDS), remembered sale type | E10: Done | F10: Development | G10: 0.16 | H10: 46239 | I10: 46239 | J10: =I10-H10+1 -> 1 | K10: 1 | L10: commits c86abb0, f10021c
A11: 6 | B11: Foundations | C11: Back office foundation | D11: Sign-in, dashboard, price editing, device enrolment | E11: Done | F11: Development | G11: 0.16 | H11: 46239 | I11: 46239 | J11: =I11-H11+1 -> 1 | K11: 1 | L11: commit c86abb0
A12: 7 | B12: Foundations | C12: Real catalog migration | D12: 560 products, 42 screens, 11 sale types loaded from the customer's PixelPoint data | E12: Done | F12: Development | G12: 0.16 | H12: 46239 | I12: 46239 | J12: =I12-H12+1 -> 1 | K12: 1 | L12: commit cd551a3
A13: 8 | B13: Catalog & menu | C13: Order numbers | D13: Reserved in blocks from the backend so two tills never call the same number | E13: Done | F13: Development | G13: 0.16 | H13: 46244 | I13: 46244 | J13: =I13-H13+1 -> 1 | K13: 1 | L13: commit b3e47b0
A14: 9 | B14: Catalog & menu | C14: Tablet schema migrations | D14: An installed till survives an app update instead of failing on a missing column | E14: Done | F14: Development | G14: 0.16 | H14: 46244 | I14: 46244 | J14: =I14-H14+1 -> 1 | K14: 1 | L14: commit 7fccf52
A15: 10 | B15: Catalog & menu | C15: Product master | D15: Products, prices across 10 tiers, kitchen routing, report category, till button look | E15: Done | F15: Development | G15: 0.16 | H15: 46244 | I15: 46244 | J15: =I15-H15+1 -> 1 | K15: 1 | L15: commits a5a43ac, 8a94a27
A16: 11 | B16: Catalog & menu | C16: Menu layout editor | D16: Pages, the menu grid a till lands on, drag-free placement of buttons | E16: Done | F16: Development | G16: 0.16 | H16: 46244 | I16: 46244 | J16: =I16-H16+1 -> 1 | K16: 1 | L16: commits c2d002c, 7b7fe66, 14340f2
A17: 12 | B17: Catalog & menu | C17: Modifiers on the till | D17: Meal-deal prompts asked before an item can be rung; choices reach the bill and the kitchen | E17: Done | F17: Development | G17: 0.16 | H17: 46244 | I17: 46244 | J17: =I17-H17+1 -> 1 | K17: 1 | L17: commits 8b29bbf, a6fc72d
... A43: 38 | B43: Compliance & release | C43: Zero-priced products review | D43: 68 products carry no price on the paying tier and cannot be sold. | E43: Not started | F43: Development | G43: 1 | H43: 46261 | I43: 46261 | J43: =I43-H43+1 -> 1 | K43: 0 | L43: 68 products carry no price on the paying tier and cannot be sold. Needs the customer to decide each one before go-live.
F45: TOTAL | G45: =SUM(G6:G43) -> 17.53 | K45: =SUMPRODUCT(G6:G43,K6:K43)/G45 -> 0.36360525 | L45: Weighted by effort, so a large workstream counts for more than a small one.

Sheet Summary
A1: Summary
A2: Every figure here is a formula over the Project Plan sheet.
A4: By status
A5: Status | B5: Workstreams | C5: Effort (days) | D5: Share of effort
A6: Done | B6: =COUNTIF('Project Plan'!$E$6:$E$43,$A6) -> 21 | C6: =SUMIF('Project Plan'!$E$6:$E$43,$A6,'Project Plan'!$G$6:$G$43) -> 4.74 | D6: =C6/$C$9 -> 0.27039361
A7: In progress | B7: =COUNTIF('Project Plan'!$E$6:$E$43,$A7) -> 9 | C7: =SUMIF('Project Plan'!$E$6:$E$43,$A7,'Project Plan'!$G$6:$G$43) -> 5.13 | D7: =C7/$C$9 -> 0.29264119
A8: Not started | B8: =COUNTIF('Project Plan'!$E$6:$E$43,$A8) -> 8 | C8: =SUMIF('Project Plan'!$E$6:$E$43,$A8,'Project Plan'!$G$6:$G$43) -> 7.66 | D8: =C8/$C$9 -> 0.4369652
A9: TOTAL | B9: =SUM(B6:B8) -> 38 | C9: =SUM(C6:C8) -> 17.53 | D9: =SUM(D6:D8) -> 1
A11: By phase
A12: Phase | B12: Workstreams | C12: Effort (days) | D12: % complete
A13: Foundations | B13: =COUNTIF('Project Plan'!$B$6:$B$43,$A13) -> 7 | C13: =SUMIF('Project Plan'!$B$6:$B$43,$A13,'Project Plan'!$G$6:$G$43) -> 1.96 | D13: =IF(C13=0,0,SUMPRODUCT(('Project Plan'!$B$6:$B$43=$A13)*'Project Plan'!$G$6:$G$43*'Project Plan'!$K$6:$K$43)/C13) -> 1
A14: Catalog & menu | B14: =COUNTIF('Project Plan'!$B$6:$B$43,$A14) -> 6 | C14: =SUMIF('Project Plan'!$B$6:$B$43,$A14,'Project Plan'!$G$6:$G$43) -> 0.94 | D14: =IF(C14=0,0,SUMPRODUCT(('Project Plan'!$B$6:$B$43=$A14)*'Project Plan'!$G$6:$G$43*'Project Plan'!$K$6:$K$43)/C14) -> 1
A15: Payments & service | B15: =COUNTIF('Project Plan'!$B$6:$B$43,$A15) -> 8 | C15: =SUMIF('Project Plan'!$B$6:$B$43,$A15,'Project Plan'!$G$6:$G$43) -> 1.84 | D15: =IF(C15=0,0,SUMPRODUCT(('Project Plan'!$B$6:$B$43=$A15)*'Project Plan'!$G$6:$G$43*'Project Plan'!$K$6:$K$43)/C15) -> 1
A16: Setup modules | B16: =COUNTIF('Project Plan'!$B$6:$B$43,$A16) -> 9 | C16: =SUMIF('Project Plan'!$B$6:$B$43,$A16,'Project Plan'!$G$6:$G$43) -> 3.79 | D16: =IF(C16=0,0,SUMPRODUCT(('Project Plan'!$B$6:$B$43=$A16)*'Project Plan'!$G$6:$G$43*'Project Plan'!$K$6:$K$43)/C16) -> 0.12770449
A17: Devices | B17: =COUNTIF('Project Plan'!$B$6:$B$43,$A17) -> 2 | C17: =SUMIF('Project Plan'!$B$6:$B$43,$A17,'Project Plan'!$G$6:$G$43) -> 2 | D17: =IF(C17=0,0,SUMPRODUCT(('Project Plan'!$B$6:$B$43=$A17)*'Project Plan'!$G$6:$G$43*'Project Plan'!$K$6:$K$43)/C17) -> 0.425
A18: Reporting | B18: =COUNTIF('Project Plan'!$B$6:$B$43,$A18) -> 1 | C18: =SUMIF('Project Plan'!$B$6:$B$43,$A18,'Project Plan'!$G$6:$G$43) -> 2 | D18: =IF(C18=0,0,SUMPRODUCT(('Project Plan'!$B$6:$B$43=$A18)*'Project Plan'!$G$6:$G$43*'Project Plan'!$K$6:$K$43)/C18) -> 0.15
A19: Compliance & release | B19: =COUNTIF('Project Plan'!$B$6:$B$43,$A19) -> 5 | C19: =SUMIF('Project Plan'!$B$6:$B$43,$A19,'Project Plan'!$G$6:$G$43) -> 5 | D19: =IF(C19=0,0,SUMPRODUCT(('Project Plan'!$B$6:$B$43=$A19)*'Project Plan'!$G$6:$G$43*'Project Plan'!$K$6:$K$43)/C19) -> 0
A21: Milestones
A22: Milestone | B22: Date | C22: Basis
A23: Project start | B23: 46238 | C23: First commit
A24: Till selling on the real catalog | B24: 46244 | C24: 560 products, real prices, kitchen routing
A25: Dine-in complete | B25: 46245 | C25: Floor, checks, merged tables, split bills
A26: Setup modules complete | B26: =SUMPRODUCT(MAX(('Project Plan'!$B$6:$B$43="Setup modules")*'Project Plan'!$I$6:$I$43)) -> 46251 | C26: End of the Setup modules phase — estimate
A27: Reporting complete | B27: =SUMPRODUCT(MAX(('Project Plan'!$B$6:$B$43="Reporting")*'Project Plan'!$I$6:$I$43)) -> 46254 | C27: End of the Reporting phase — estimate
A28: Ready for go-live | B28: 46337 | C28: After compliance and release work — ESTIMATE, and gated by ZATCA onboarding which needs the customer's Fatoora credentials

Sheet Timeline
A1: Timeline
A2: One column per week. A bar is drawn by formula from the Start and Finish on the Project Plan sheet, so editing a date there redraws the bar here. | C2: 46236 | D2: 46243 | E2: 46250 | F2: 46257 | G2: 46264 | H2: 46271 | I2: 46278 | J2: 46285 | K2: 46292 | L2: 46299 | M2: 46306 | N2: 46313 | O2: 46320 | P2: 46327
C3: 46242 | D3: 46249 | E3: 46256 | F3: 46263 | G3: 46270 | H3: 46277 | I3: 46284 | J3: 46291 | K3: 46298 | L3: 46305 | M3: 46312 | N3: 46319 | O3: 46326 | P3: 46333
A4: Workstream | B4: Status | C4: 02 Aug | D4: 09 Aug | E4: 16 Aug | F4: 23 Aug | G4: 30 Aug | H4: 06 Sep | I4: 13 Sep | J4: 20 Sep | K4: 27 Sep | L4: 04 Oct | M4: 11 Oct | N4: 18 Oct | O4: 25 Oct | P4: 01 Nov
A5: ='Project Plan'!C6 -> Architecture & repository | B5: ='Project Plan'!E6 -> Done | C5: =IF(AND('Project Plan'!$H6<=C$3,'Project Plan'!$I6>=C$2),"█","") -> █ | D5: =IF(AND('Project Plan'!$H6<=D$3,'Project Plan'!$I6>=D$2),"█","") | E5: =IF(AND('Project Plan'!$H6<=E$3,'Project Plan'!$I6>=E$2),"█","") | F5: =IF(AND('Project Plan'!$H6<=F$3,'Project Plan'!$I6>=F$2),"█","") | G5: =IF(AND('Project Plan'!$H6<=G$3,'Project Plan'!$I6>=G$2),"█","") | H5: =IF(AND('Project Plan'!$H6<=H$3,'Project Plan'!$I6>=H$2),"█","") | I5: =IF(AND('Project Plan'!$H6<=I$3,'Project Plan'!$I6>=I$2),"█","") | J5: =IF(AND('Project Plan'!$H6<=J$3,'Project Plan'!$I6>=J$2),"█","") | ... P5: =IF(AND('Project Plan'!$H6<=P$3,'Project Plan'!$I6>=P$2),"█","")
A6: ='Project Plan'!C7 -> ZATCA signing on the device | B6: ='Project Plan'!E7 -> Done | C6: =IF(AND('Project Plan'!$H7<=C$3,'Project Plan'!$I7>=C$2),"█","") -> █ | D6: =IF(AND('Project Plan'!$H7<=D$3,'Project Plan'!$I7>=D$2),"█","") | E6: =IF(AND('Project Plan'!$H7<=E$3,'Project Plan'!$I7>=E$2),"█","") | F6: =IF(AND('Project Plan'!$H7<=F$3,'Project Plan'!$I7>=F$2),"█","") | G6: =IF(AND('Project Plan'!$H7<=G$3,'Project Plan'!$I7>=G$2),"█","") | H6: =IF(AND('Project Plan'!$H7<=H$3,'Project Plan'!$I7>=H$2),"█","") | I6: =IF(AND('Project Plan'!$H7<=I$3,'Project Plan'!$I7>=I$2),"█","") | J6: =IF(AND('Project Plan'!$H7<=J$3,'Project Plan'!$I7>=J$2),"█","") | ... P6: =IF(AND('Project Plan'!$H7<=P$3,'Project Plan'!$I7>=P$2),"█","")
A7: ='Project Plan'!C8 -> Printer Setup | B7: ='Project Plan'!E8 -> Done | C7: =IF(AND('Project Plan'!$H8<=C$3,'Project Plan'!$I8>=C$2),"█","") -> █ | D7: =IF(AND('Project Plan'!$H8<=D$3,'Project Plan'!$I8>=D$2),"█","") | E7: =IF(AND('Project Plan'!$H8<=E$3,'Project Plan'!$I8>=E$2),"█","") | F7: =IF(AND('Project Plan'!$H8<=F$3,'Project Plan'!$I8>=F$2),"█","") | G7: =IF(AND('Project Plan'!$H8<=G$3,'Project Plan'!$I8>=G$2),"█","") | H7: =IF(AND('Project Plan'!$H8<=H$3,'Project Plan'!$I8>=H$2),"█","") | I7: =IF(AND('Project Plan'!$H8<=I$3,'Project Plan'!$I8>=I$2),"█","") | J7: =IF(AND('Project Plan'!$H8<=J$3,'Project Plan'!$I8>=J$2),"█","") | ... P7: =IF(AND('Project Plan'!$H8<=P$3,'Project Plan'!$I8>=P$2),"█","")
A8: ='Project Plan'!C9 -> Windows desktop target | B8: ='Project Plan'!E9 -> Done | C8: =IF(AND('Project Plan'!$H9<=C$3,'Project Plan'!$I9>=C$2),"█","") -> █ | D8: =IF(AND('Project Plan'!$H9<=D$3,'Project Plan'!$I9>=D$2),"█","") | E8: =IF(AND('Project Plan'!$H9<=E$3,'Project Plan'!$I9>=E$2),"█","") | F8: =IF(AND('Project Plan'!$H9<=F$3,'Project Plan'!$I9>=F$2),"█","") | G8: =IF(AND('Project Plan'!$H9<=G$3,'Project Plan'!$I9>=G$2),"█","") | H8: =IF(AND('Project Plan'!$H9<=H$3,'Project Plan'!$I9>=H$2),"█","") | I8: =IF(AND('Project Plan'!$H9<=I$3,'Project Plan'!$I9>=I$2),"█","") | J8: =IF(AND('Project Plan'!$H9<=J$3,'Project Plan'!$I9>=J$2),"█","") | ... P8: =IF(AND('Project Plan'!$H9<=P$3,'Project Plan'!$I9>=P$2),"█","")
A9: ='Project Plan'!C10 -> Till Setup / device enrolment | B9: ='Project Plan'!E10 -> Done | C9: =IF(AND('Project Plan'!$H10<=C$3,'Project Plan'!$I10>=C$2),"█","") -> █ | D9: =IF(AND('Project Plan'!$H10<=D$3,'Project Plan'!$I10>=D$2),"█","") | E9: =IF(AND('Project Plan'!$H10<=E$3,'Project Plan'!$I10>=E$2),"█","") | F9: =IF(AND('Project Plan'!$H10<=F$3,'Project Plan'!$I10>=F$2),"█","") | G9: =IF(AND('Project Plan'!$H10<=G$3,'Project Plan'!$I10>=G$2),"█","") | H9: =IF(AND('Project Plan'!$H10<=H$3,'Project Plan'!$I10>=H$2),"█","") | I9: =IF(AND('Project Plan'!$H10<=I$3,'Project Plan'!$I10>=I$2),"█","") | J9: =IF(AND('Project Plan'!$H10<=J$3,'Project Plan'!$I10>=J$2),"█","") | ... P9: =IF(AND('Project Plan'!$H10<=P$3,'Project Plan'!$I10>=P$2),"█","")
A10: ='Project Plan'!C11 -> Back office foundation | B10: ='Project Plan'!E11 -> Done | C10: =IF(AND('Project Plan'!$H11<=C$3,'Project Plan'!$I11>=C$2),"█","") -> █ | D10: =IF(AND('Project Plan'!$H11<=D$3,'Project Plan'!$I11>=D$2),"█","") | E10: =IF(AND('Project Plan'!$H11<=E$3,'Project Plan'!$I11>=E$2),"█","") | F10: =IF(AND('Project Plan'!$H11<=F$3,'Project Plan'!$I11>=F$2),"█","") | G10: =IF(AND('Project Plan'!$H11<=G$3,'Project Plan'!$I11>=G$2),"█","") | H10: =IF(AND('Project Plan'!$H11<=H$3,'Project Plan'!$I11>=H$2),"█","") | I10: =IF(AND('Project Plan'!$H11<=I$3,'Project Plan'!$I11>=I$2),"█","") | J10: =IF(AND('Project Plan'!$H11<=J$3,'Project Plan'!$I11>=J$2),"█","") | ... P10: =IF(AND('Project Plan'!$H11<=P$3,'Project Plan'!$I11>=P$2),"█","")
A11: ='Project Plan'!C12 -> Real catalog migration | B11: ='Project Plan'!E12 -> Done | C11: =IF(AND('Project Plan'!$H12<=C$3,'Project Plan'!$I12>=C$2),"█","") -> █ | D11: =IF(AND('Project Plan'!$H12<=D$3,'Project Plan'!$I12>=D$2),"█","") | E11: =IF(AND('Project Plan'!$H12<=E$3,'Project Plan'!$I12>=E$2),"█","") | F11: =IF(AND('Project Plan'!$H12<=F$3,'Project Plan'!$I12>=F$2),"█","") | G11: =IF(AND('Project Plan'!$H12<=G$3,'Project Plan'!$I12>=G$2),"█","") | H11: =IF(AND('Project Plan'!$H12<=H$3,'Project Plan'!$I12>=H$2),"█","") | I11: =IF(AND('Project Plan'!$H12<=I$3,'Project Plan'!$I12>=I$2),"█","") | J11: =IF(AND('Project Plan'!$H12<=J$3,'Project Plan'!$I12>=J$2),"█","") | ... P11: =IF(AND('Project Plan'!$H12<=P$3,'Project Plan'!$I12>=P$2),"█","")
A12: ='Project Plan'!C13 -> Order numbers | B12: ='Project Plan'!E13 -> Done | C12: =IF(AND('Project Plan'!$H13<=C$3,'Project Plan'!$I13>=C$2),"█","") | D12: =IF(AND('Project Plan'!$H13<=D$3,'Project Plan'!$I13>=D$2),"█","") -> █ | E12: =IF(AND('Project Plan'!$H13<=E$3,'Project Plan'!$I13>=E$2),"█","") | F12: =IF(AND('Project Plan'!$H13<=F$3,'Project Plan'!$I13>=F$2),"█","") | G12: =IF(AND('Project Plan'!$H13<=G$3,'Project Plan'!$I13>=G$2),"█","") | H12: =IF(AND('Project Plan'!$H13<=H$3,'Project Plan'!$I13>=H$2),"█","") | I12: =IF(AND('Project Plan'!$H13<=I$3,'Project Plan'!$I13>=I$2),"█","") | J12: =IF(AND('Project Plan'!$H13<=J$3,'Project Plan'!$I13>=J$2),"█","") | ... P12: =IF(AND('Project Plan'!$H13<=P$3,'Project Plan'!$I13>=P$2),"█","")
A13: ='Project Plan'!C14 -> Tablet schema migrations | B13: ='Project Plan'!E14 -> Done | C13: =IF(AND('Project Plan'!$H14<=C$3,'Project Plan'!$I14>=C$2),"█","") | D13: =IF(AND('Project Plan'!$H14<=D$3,'Project Plan'!$I14>=D$2),"█","") -> █ | E13: =IF(AND('Project Plan'!$H14<=E$3,'Project Plan'!$I14>=E$2),"█","") | F13: =IF(AND('Project Plan'!$H14<=F$3,'Project Plan'!$I14>=F$2),"█","") | G13: =IF(AND('Project Plan'!$H14<=G$3,'Project Plan'!$I14>=G$2),"█","") | H13: =IF(AND('Project Plan'!$H14<=H$3,'Project Plan'!$I14>=H$2),"█","") | I13: =IF(AND('Project Plan'!$H14<=I$3,'Project Plan'!$I14>=I$2),"█","") | J13: =IF(AND('Project Plan'!$H14<=J$3,'Project Plan'!$I14>=J$2),"█","") | ... P13: =IF(AND('Project Plan'!$H14<=P$3,'Project Plan'!$I14>=P$2),"█","")
A14: ='Project Plan'!C15 -> Product master | B14: ='Project Plan'!E15 -> Done | C14: =IF(AND('Project Plan'!$H15<=C$3,'Project Plan'!$I15>=C$2),"█","") | D14: =IF(AND('Project Plan'!$H15<=D$3,'Project Plan'!$I15>=D$2),"█","") -> █ | E14: =IF(AND('Project Plan'!$H15<=E$3,'Project Plan'!$I15>=E$2),"█","") | F14: =IF(AND('Project Plan'!$H15<=F$3,'Project Plan'!$I15>=F$2),"█","") | G14: =IF(AND('Project Plan'!$H15<=G$3,'Project Plan'!$I15>=G$2),"█","") | H14: =IF(AND('Project Plan'!$H15<=H$3,'Project Plan'!$I15>=H$2),"█","") | I14: =IF(AND('Project Plan'!$H15<=I$3,'Project Plan'!$I15>=I$2),"█","") | J14: =IF(AND('Project Plan'!$H15<=J$3,'Project Plan'!$I15>=J$2),"█","") | ... P14: =IF(AND('Project Plan'!$H15<=P$3,'Project Plan'!$I15>=P$2),"█","")
A15: ='Project Plan'!C16 -> Menu layout editor | B15: ='Project Plan'!E16 -> Done | C15: =IF(AND('Project Plan'!$H16<=C$3,'Project Plan'!$I16>=C$2),"█","") | D15: =IF(AND('Project Plan'!$H16<=D$3,'Project Plan'!$I16>=D$2),"█","") -> █ | E15: =IF(AND('Project Plan'!$H16<=E$3,'Project Plan'!$I16>=E$2),"█","") | F15: =IF(AND('Project Plan'!$H16<=F$3,'Project Plan'!$I16>=F$2),"█","") | G15: =IF(AND('Project Plan'!$H16<=G$3,'Project Plan'!$I16>=G$2),"█","") | H15: =IF(AND('Project Plan'!$H16<=H$3,'Project Plan'!$I16>=H$2),"█","") | I15: =IF(AND('Project Plan'!$H16<=I$3,'Project Plan'!$I16>=I$2),"█","") | J15: =IF(AND('Project Plan'!$H16<=J$3,'Project Plan'!$I16>=J$2),"█","") | ... P15: =IF(AND('Project Plan'!$H16<=P$3,'Project Plan'!$I16>=P$2),"█","")
A16: ='Project Plan'!C17 -> Modifiers on the till | B16: ='Project Plan'!E17 -> Done | C16: =IF(AND('Project Plan'!$H17<=C$3,'Project Plan'!$I17>=C$2),"█","") | D16: =IF(AND('Project Plan'!$H17<=D$3,'Project Plan'!$I17>=D$2),"█","") -> █ | E16: =IF(AND('Project Plan'!$H17<=E$3,'Project Plan'!$I17>=E$2),"█","") | F16: =IF(AND('Project Plan'!$H17<=F$3,'Project Plan'!$I17>=F$2),"█","") | G16: =IF(AND('Project Plan'!$H17<=G$3,'Project Plan'!$I17>=G$2),"█","") | H16: =IF(AND('Project Plan'!$H17<=H$3,'Project Plan'!$I17>=H$2),"█","") | I16: =IF(AND('Project Plan'!$H17<=I$3,'Project Plan'!$I17>=I$2),"█","") | J16: =IF(AND('Project Plan'!$H17<=J$3,'Project Plan'!$I17>=J$2),"█","") | ... P16: =IF(AND('Project Plan'!$H17<=P$3,'Project Plan'!$I17>=P$2),"█","")
... A42: ='Project Plan'!C43 -> Zero-priced products review | B42: ='Project Plan'!E43 -> Not started | C42: =IF(AND('Project Plan'!$H43<=C$3,'Project Plan'!$I43>=C$2),"█","") | D42: =IF(AND('Project Plan'!$H43<=D$3,'Project Plan'!$I43>=D$2),"█","") | E42: =IF(AND('Project Plan'!$H43<=E$3,'Project Plan'!$I43>=E$2),"█","") | F42: =IF(AND('Project Plan'!$H43<=F$3,'Project Plan'!$I43>=F$2),"█","") -> █ | G42: =IF(AND('Project Plan'!$H43<=G$3,'Project Plan'!$I43>=G$2),"█","") | H42: =IF(AND('Project Plan'!$H43<=H$3,'Project Plan'!$I43>=H$2),"█","") | I42: =IF(AND('Project Plan'!$H43<=I$3,'Project Plan'!$I43>=I$2),"█","") | J42: =IF(AND('Project Plan'!$H43<=J$3,'Project Plan'!$I43>=J$2),"█","") | ... P42: =IF(AND('Project Plan'!$H43<=P$3,'Project Plan'!$I43>=P$2),"█","")

Sheet Assumptions
A1: Assumptions, and how to read this plan
A3: Where the delivered dates come from | B3: The commit history of the repository, 4–12 August 2026. They are what happened, not estimates. Each delivered row names its commit in the Evidence column.
A4: Where the remaining dates come from | B4: Estimates, shown in blue everywhere they appear. They are the author's sizing of the remaining work, sequenced one item after another, and they are the least reliable numbers in this workbook.
A5: Working week | B5: Sunday to Thursday. Friday and Saturday are treated as the weekend. Public holidays are NOT deducted — add them and the finish dates move out.
A6: Team size | B6: One developer, working serially. Reports and Kiosk Setup share no dependencies with the setup modules, so a second developer could run them in parallel and pull the go-live date in by roughly three weeks.
A7: What "In progress" means here | B7: Part of the workstream is already live and part is not. The % complete column says how much, and the Notes column says exactly which part is missing. Six of the fourteen items on the client's list are in this state — none of them is starting from nothing.
A8: What is NOT in the estimates | B8: User acceptance testing, staff training, data cleansing beyond the 68 zero-priced products, hardware procurement, and on-site installation.
A9: The dependency that is not ours | B9: ZATCA phase-2 onboarding needs the customer's Fatoora portal credentials. Until those exist the till signs with a placeholder certificate, and no amount of development moves that date.
A10: Additional items beyond the client's list | B10: Arabic receipts, the Android build, the single-instance guard, ZATCA onboarding and the zero-priced product review are included because go-live depends on them. They were not on the list supplied.
A11: Effort vs duration | B11: Effort is working days of development. Calendar days on the plan sheet is the span from start to finish including weekends, and is a formula.
